dcp_vga/__init__.py
dcp_vga/src/__init__.py
dcp_vga/src/vga.py
dcp_vga/src/models/__init__.py
dcp_vga/src/operations/__init__.py
dcp_vga/src/operations/crossover.py
dcp_vga/src/operations/mutations.py
dcp_vga/src/operations/selection.py
dcp_vga-0.0.1.dist-info/LICENSE
dcp_vga-0.0.1.dist-info/METADATA
dcp_vga-0.0.1.dist-info/WHEEL
dcp_vga-0.0.1.dist-info/top_level.txt
dcp_vga-0.0.1.dist-info/RECORD
