Metadata-Version: 2.1
Name: dcp_vga
Version: 0.0.1
Summary: A varying-length genetic algorithm approach to dynamic convolutional partitioning
Author-email: Yusuf Sulehman <yusuf.sulehman@postgrad.manchester.ac.uk>
Project-URL: Homepage, https://github.com/YSulehman/dcp_vga
Classifier: Programming Language :: Python :: 3
Classifier: License :: OSI Approved :: MIT License
Classifier: Operating System :: OS Independent
Requires-Python: >=3.8
License-File: LICENSE
